Blooker
