Metadata-Version: 2.1
Name: Blooker
Version: 0.0.5
Summary: Flood Blooket Games
Home-page: https://github.com/bigboy-baby/
Author: Biggie
Author-email: thugshaker@yahoo.com
Requires-Python: >=3
